AUTHORS.rst
CHANGES.rst
LICENSE
sphinxcontrib/__init__.py
sphinxcontrib/nvd3/__init__.py
sphinxcontrib/nvd3/directives.py
sphinxcontrib.nvd3-0.2.1.dist-info/LICENSE
sphinxcontrib.nvd3-0.2.1.dist-info/WHEEL
sphinxcontrib.nvd3-0.2.1.dist-info/METADATA
sphinxcontrib.nvd3-0.2.1.dist-info/RECORD
