Metadata-Version: 2.1
Name: sphinxcontrib.nvd3
Version: 0.2.1
Summary: Sphinx chart extension using NVD3.js.
Home-page: https://github.com/shkumagai/sphinxcontrib.nvd3
License: Apache Software License
Author: shkumagai
Author-email: take.this.2.your.grave@gmail.com
Requires-Python: >=3.6,<4.0
Classifier: Development Status :: 4 - Beta
Classifier: Environment :: Web Environment
Classifier: Framework :: Sphinx
Classifier: Framework :: Sphinx :: Extension
Classifier: Intended Audience :: Developers
Classifier: License :: OSI Approved :: Apache Software License
Classifier: License :: Other/Proprietary License
Classifier: Programming Language :: Python
Classifier: Programming Language :: Python :: 3
Classifier: Programming Language :: Python :: 3 :: Only
Classifier: Programming Language :: Python :: 3.6
Classifier: Programming Language :: Python :: 3.7
Classifier: Programming Language :: Python :: 3.8
Classifier: Programming Language :: Python :: 3.9
Classifier: Topic :: Documentation
Classifier: Topic :: Documentation :: Sphinx
Classifier: Topic :: Software Development
Classifier: Topic :: Software Development :: Documentation
Classifier: Topic :: Text Processing :: Markup
Requires-Dist: Sphinx (>=3.5.0,<4.0.0)
Requires-Dist: python-nvd3 (>=0.15.0,<0.16.0)
